smoking_gun
