Metadata-Version: 2.1
Name: smoking-gun
Version: 1.0.1
Summary: The log capturing library.
Home-page: https://github.com/dopstar/smoking-gun
Author: Mkhanyisi Madlavana
Author-email: mmadlavana@gmail.com
License: MIT License
Download-URL: https://github.com/dopstar/smoking-gun/archive/1.0.1.tar.gz
Keywords: Smoking,Gun,profiling,tracing,logging
Platform: UNKNOWN
Classifier: Development Status :: 5 - Production/Stable
Classifier: Intended Audience :: Developers
Classifier: Natural Language :: English
Classifier: Programming Language :: Python
Classifier: Programming Language :: Python :: 2.7
Classifier: Programming Language :: Python :: 3.6
Classifier: Programming Language :: Python :: 3.7
Classifier: Programming Language :: Python :: 3.8
Classifier: License :: OSI Approved :: MIT License
Classifier: Operating System :: MacOS
Classifier: Operating System :: POSIX :: Linux
Classifier: Operating System :: Microsoft :: Windows
Classifier: Topic :: Software Development :: Version Control :: Git
Classifier: Programming Language :: Python :: Implementation :: CPython
Provides-Extra: testing
Provides-Extra: linting
